MANIFEST.in
README.rst
setup.py
infobase/__init__.py
infobase/infobase.py
infobase.egg-info/PKG-INFO
infobase.egg-info/SOURCES.txt
infobase.egg-info/dependency_links.txt
infobase.egg-info/not-zip-safe
infobase.egg-info/requires.txt
infobase.egg-info/top_level.txt