Metadata-Version: 1.1
Name: infobase
Version: 0.8.Alpha
Summary: A Minimalistic Database System in Python
Home-page: encry.cpnerd.koding.io/infobase.py
Author: CPNerd
Author-email: shadow889566@gmail.com
License: MIT
Platform: UNKNOWN
Classifier: Development Status :: 3 - Alpha
Classifier: License :: OSI Approved :: MIT License
Classifier: Programming Language :: Python :: 2.7
Classifier: Intended Audience :: Developers
